conf.py
derobertis_cv/__init__.py
derobertis_cv/logger.py
derobertis_cv/models/__init__.py
derobertis_cv/models/award.py
derobertis_cv/models/cased.py
derobertis_cv/models/category.py
derobertis_cv/models/course.py
derobertis_cv/models/experience_scale.py
derobertis_cv/models/grades/__init__.py
derobertis_cv/models/grades/breakdown.py
derobertis_cv/models/grades/main.py
derobertis_cv/models/grades/scale.py
derobertis_cv/models/i_skill_experience.py
derobertis_cv/models/level_scale.py
derobertis_cv/models/nested.py
derobertis_cv/models/organization.py
derobertis_cv/models/prereq.py
derobertis_cv/models/resources.py
derobertis_cv/models/skill.py
derobertis_cv/models/skill_experience.py
derobertis_cv/models/skill_experience_mixin.py
derobertis_cv/models/skill_experiences.py
derobertis_cv/models/textbook.py
derobertis_cv/models/university.py
derobertis_cv/pdf_compressor.py
derobertis_cv/plbuild/__init__.py
derobertis_cv/plbuild/assets/images/call-option-logo.svg
derobertis_cv/plbuild/assets/images/cfa-logo.svg
derobertis_cv/plbuild/assets/images/chart-line-down.svg
derobertis_cv/plbuild/assets/images/cryptocompare.png
derobertis_cv/plbuild/assets/images/datastream.png
derobertis_cv/plbuild/assets/images/drawing.svg
derobertis_cv/plbuild/assets/images/excel.png
derobertis_cv/plbuild/assets/images/gmat-logo.svg
derobertis_cv/plbuild/assets/images/insider.svg
derobertis_cv/plbuild/assets/images/nd-logo-site-link.png
derobertis_cv/plbuild/assets/images/nd-logo-site-link.xcf
derobertis_cv/plbuild/assets/images/nd-logo.png
derobertis_cv/plbuild/assets/images/nick-derobertis.png
derobertis_cv/plbuild/assets/images/portfolio-analysis-logo.svg
derobertis_cv/plbuild/assets/images/sec-logo.png
derobertis_cv/plbuild/assets/images/sigma-lower.svg
derobertis_cv/plbuild/assets/images/signature.png
derobertis_cv/plbuild/assets/images/sp-capital-iq.png
derobertis_cv/plbuild/assets/images/svelte-angular.png
derobertis_cv/plbuild/assets/images/svelte-angular.xcf
derobertis_cv-1.5.0.dist-info/WHEEL
derobertis_cv-1.5.0.dist-info/LICENSE.md
derobertis_cv-1.5.0.dist-info/METADATA
derobertis_cv-1.5.0.dist-info/RECORD
