Metadata-Version: 2.1
Name: derobertis-cv
Version: 1.5.0
Summary: Nick DeRobertis' CV Data and pyexlatex Build
License: MIT
Author: Nick DeRobertis
Author-email: whoopnip@gmail.com
Requires-Python: >=3.10
Classifier: Development Status :: 3 - Alpha
Classifier: Intended Audience :: Developers
Classifier: License :: OSI Approved :: MIT License
Classifier: Programming Language :: Python :: 3
Classifier: Programming Language :: Python :: 3.10
Classifier: Programming Language :: Python :: 3.11
Classifier: Programming Language :: Python :: 3.10
Classifier: Programming Language :: Python :: 3.11
Classifier: Programming Language :: Python :: 3.7
Classifier: Programming Language :: Python :: 3.8
Classifier: Programming Language :: Python :: 3.9
Requires-Dist: PyPDF2 (<3)
Requires-Dist: PythonVideoConverter
Requires-Dist: inflect
Requires-Dist: jupyter-client
Requires-Dist: jupyterlab
Requires-Dist: pl-builder (<1)
Requires-Dist: project-report (==1.0.0a11)
Requires-Dist: pydantic (<2)
Requires-Dist: pygithub (==1.55)
Requires-Dist: pyyaml
Requires-Dist: rich
Requires-Dist: types-pyyaml
Requires-Dist: types-requests
Requires-Dist: weakreflist
Project-URL: documentation, https://nickderobertis.github.io/derobertis-cv
Project-URL: repository, https://github.com/nickderobertis/derobertis-cv
